planarfibers/__init__.py
planarfibers/approximation.py
planarfibers/averager.py
planarfibers/discretization.py
planarfibers/notation.py
planarfibers/utils.py
planarfibers-0.0.2.dist-info/LICENSE
planarfibers-0.0.2.dist-info/METADATA
planarfibers-0.0.2.dist-info/WHEEL
planarfibers-0.0.2.dist-info/top_level.txt
planarfibers-0.0.2.dist-info/RECORD
