Metadata-Version: 2.1
Name: planarfibers
Version: 0.0.2
Summary: PlanarFibers contains selected contributions of Bauer, Julian Karl, and Thomas Böhlke. 'On the dependence of orientation averaging mean field homogenization on planar fourth-order fiber orientation tensors.' Mechanics of Materials (2022): 104307.
Home-page: https://github.com/JulianKarlBauer/orientation_averaging_mean_field
Author: Julian Karl Bauer
Author-email: juliankarlbauer@gmx.de
License: UNKNOWN
Platform: UNKNOWN
Classifier: Programming Language :: Python :: 3
Classifier: Operating System :: OS Independent
License-File: LICENSE
Requires-Dist: numpy
Requires-Dist: scipy
Requires-Dist: sympy
Requires-Dist: pandas
Requires-Dist: matplotlib
Requires-Dist: mechmean
Requires-Dist: mechkit
